adafruit_thermal_printer/__init__.py
adafruit_thermal_printer/thermal_printer.py
adafruit_thermal_printer/thermal_printer_2168.py
adafruit_thermal_printer/thermal_printer_264.py
adafruit_thermal_printer/thermal_printer_legacy.py
adafruit_circuitpython_thermal_printer-1.4.0.dist-info/LICENSE
adafruit_circuitpython_thermal_printer-1.4.0.dist-info/METADATA
adafruit_circuitpython_thermal_printer-1.4.0.dist-info/WHEEL
adafruit_circuitpython_thermal_printer-1.4.0.dist-info/top_level.txt
adafruit_circuitpython_thermal_printer-1.4.0.dist-info/RECORD
