Metadata-Version: 2.1
Name: adafruit-circuitpython-thermal-printer
Version: 1.4.0
Summary: CircuitPython library for controlling thermal printers.
Author-email: Adafruit Industries <circuitpython@adafruit.com>
License: MIT
Project-URL: Homepage, https://github.com/adafruit/Adafruit_CircuitPython_Thermal_Printer
Keywords: adafruit,thermal,printer,hardware,micropython,circuitpython
Classifier: Intended Audience :: Developers
Classifier: Topic :: Software Development :: Libraries
Classifier: Topic :: Software Development :: Embedded Systems
Classifier: Topic :: System :: Hardware
Classifier: License :: OSI Approved :: MIT License
Classifier: Programming Language :: Python :: 3
License-File: LICENSE
Requires-Dist: Adafruit-Blinka
Requires-Dist: pyserial
Requires-Dist: adafruit-circuitpython-typing
Requires-Dist: typing-extensions (~=4.0)
Provides-Extra: optional
